htmd_py-0.1.0.dist-info/METADATA
htmd_py-0.1.0.dist-info/WHEEL
htmd_py-0.1.0.dist-info/licenses/LICENSE
htmd.libs/libgcc_s-b5472b99.so.1
htmd/__init__.py
htmd/htmd.cpython-39-i386-linux-gnu.so
htmd_py-0.1.0.dist-info/RECORD
