Metadata-Version: 2.4
Name: htmd-py
Version: 0.1.0
Classifier: Intended Audience :: Developers
Classifier: License :: OSI Approved :: Apache Software License
Classifier: Programming Language :: Rust
Classifier: Programming Language :: Python :: Implementation :: CPython
Classifier: Programming Language :: Python :: Implementation :: PyPy
Classifier: Operating System :: OS Independent
Classifier: Programming Language :: Python :: 3
Classifier: Programming Language :: Python :: 3.10
Classifier: Programming Language :: Python :: 3.11
Classifier: Programming Language :: Python :: 3.12
Classifier: Programming Language :: Python :: 3.13
Classifier: Programming Language :: Python :: 3.9
Requires-Dist: maturin[patchelf]>=1.8.2 ; extra == 'dev'
Requires-Dist: pdm>=2.22.3 ; extra == 'dev'
Requires-Dist: pdm-bump>=0.9.10 ; extra == 'dev'
Requires-Dist: pre-commit>=4.1.0 ; extra == 'dev'
Requires-Dist: markdownify>=1.1.0 ; extra == 'bench'
Provides-Extra: dev
Provides-Extra: bench
License-File: LICENSE
Summary: Python bindings for the htmd Rust library, a fast HTML to Markdown converter
Keywords: html,markdown,rust,commonmark,parser,html2md
Author-email: Louis Maddox <louismmx@gmail.com>
Requires-Python: >=3.9
Project-URL: Homepage, https://github.com/lmmx/htmd
Project-URL: Repository, https://github.com/lmmx/htmd.git
